PSIcheck/__init__.py
PSIcheck/get_parser.py
PSIcheck/screen_for_magPro.py
PSIcheck-0.1.0.dist-info/METADATA
PSIcheck-0.1.0.dist-info/WHEEL
PSIcheck-0.1.0.dist-info/entry_points.txt
PSIcheck-0.1.0.dist-info/top_level.txt
PSIcheck-0.1.0.dist-info/RECORD
